Metadata-Version: 2.4
Name: ugbio_cnv
Version: 1.20.0
Summary: Ultima Genomics CNV utils
Author-email: Tammy Biniashvili <tammy.biniashvili@ultimagen.com>, Avigail Moldovan <avigail.moldovan@ultimagen.com>, Ilya Soifer <ilya.soifer@ultimagen.com>
License: Apache-2.0
Requires-Python: >=3.11
Requires-Dist: ugbio_core[vcfbed]
Requires-Dist: seaborn<1.0.0,>=0.13.2
Requires-Dist: cnvpytor==1.3.1
Requires-Dist: setuptools>=75.8.0
